cmb/__init__.py
cmb/_version.py
cmb/functions.py
cmb/helpers.py
cmb/source_space.py
cmb/test.py
cmb/visualization.py
cmb-0.0.7.dist-info/LICENSE
cmb-0.0.7.dist-info/METADATA
cmb-0.0.7.dist-info/WHEEL
cmb-0.0.7.dist-info/license.txt
cmb-0.0.7.dist-info/top_level.txt
cmb-0.0.7.dist-info/RECORD
