Metadata-Version: 2.1
Name: cmb
Version: 0.0.7
Summary: Cere-MEG-Bellum (CMB) - Cerbellum segmentation and forward solution calculation
Home-page: https://github.com/johnsam7/ceremegbellum
Maintainer: John Gustaf Wilhelm Samuelsson
Maintainer-email: johnsam@mit.edu
License: MIT License
Download-URL: https://github.com/johnsam7/ceremegbellum
Project-URL: Source, https://github.com/johnsam7/ceremegbellum/
Project-URL: Tracker, https://github.com/johnsam7/ceremegbellum/issues/
Keywords: neuroscience neuroimaging MEG cerebellum brain
Platform: any
Classifier: Intended Audience :: Science/Research
Classifier: Intended Audience :: Developers
Classifier: License :: OSI Approved :: MIT License
Classifier: Programming Language :: Python :: 3
Classifier: Topic :: Scientific/Engineering
Classifier: Operating System :: POSIX
Classifier: Operating System :: Unix
Classifier: Operating System :: MacOS
Classifier: Programming Language :: Python :: 3
Requires-Python: >=3.7
Requires-Dist: numpy (>=1.20.1)
Requires-Dist: scipy (>=1.6.0)
Requires-Dist: mne (>=0.22.0)
Requires-Dist: matplotlib (>=3.3.4)
Requires-Dist: nibabel (>=3.2.1)
Requires-Dist: nnunet (>=1.7.0)
Requires-Dist: plyfile (>=0.7.4)
Requires-Dist: antspyx (>=0.2.7)
Requires-Dist: pandas (>=1.2.2)
Requires-Dist: evaler (>=0.0.2)
